servicemock/__init__.py
servicemock/adapter.py
servicemock/servicemock.py
servicemock/unittest.py
tests/__init__.py
tests/test_error_messages.py
tests/test_request.py
tests/test_service_mock.py
tests/test_unittest_integration.py
tests/test_utest_example.py
servicemock-0.1.1.dist-info/LICENSE
servicemock-0.1.1.dist-info/METADATA
servicemock-0.1.1.dist-info/WHEEL
servicemock-0.1.1.dist-info/top_level.txt
servicemock-0.1.1.dist-info/RECORD
