Metadata-Version: 2.1
Name: servicemock
Version: 0.1.1
Summary: Mock DSL for requests_mock
Home-page: https://github.com/mlackman/urban-lamp
Author: Mika Lackman
Author-email: mika.lackman@gmail.com
License: UNKNOWN
Platform: UNKNOWN
Classifier: Development Status :: 3 - Alpha
Classifier: Programming Language :: Python :: 3
Classifier: License :: OSI Approved :: GNU General Public License v3 or later (GPLv3+)
Classifier: Operating System :: OS Independent
Requires-Python: >=3.7
Requires-Dist: requests (==2.23)
Requires-Dist: requests-mock (==1.8.0)
